{
    "ARN": "arn:aws:secretsmanager:us-east-1:497891874516:secret:ai-app-prd-db-secret-jjTmPm",
    "Name": "ai-app-prd-db-secret",
    "LastChangedDate": "2023-06-07T15:55:52.009000+01:00",
    "VersionIdsToStages": {
        "5d11fc00-eb78-4108-a338-e5e1a85660c8": [
            "AWSCURRENT"
        ]
    },
    "CreatedDate": "2023-06-07T15:55:51.690000+01:00",
    "ResponseMetadata": {
        "RequestId": "e8a481a2-4e9c-466f-847b-bf4ee4dad4b2",
        "HTTPStatusCode": 200,
        "HTTPHeaders": {
            "x-amzn-requestid": "e8a481a2-4e9c-466f-847b-bf4ee4dad4b2",
            "content-type": "application/x-amz-json-1.1",
            "content-length": "262",
            "date": "Wed, 07 Jun 2023 14:56:45 GMT"
        },
        "RetryAttempts": 0
    }
}